tantaroba/__init__.py
tantaroba/__version__.py
tantaroba/dates.py
tantaroba/dynamic_import.py
tantaroba/iterator_helpers.py
tantaroba/log.py
tantaroba/profile.py
tantaroba/scripts/script.py
tantaroba/strings.py
tantaroba/yaml.py
tantaroba-0.5.0.dist-info/LICENSE
tantaroba-0.5.0.dist-info/METADATA
tantaroba-0.5.0.dist-info/WHEEL
tantaroba-0.5.0.dist-info/RECORD
